[
{
"law": "総則",
"cat": "目的",
"q": "雇用保険は、政府が管掌する。",
"a": true,
"exp": "〇。法2条。雇用保険は政府が管掌し、その事務の一部は都道府県知事が行うこととすることができる。",
"page": 14
},
{
"law": "総則",
"cat": "目的",
"q": "雇用保険は、目的を達成するため、失業等給付及び育児休業等給付を行うほか、<b>雇用安定事業及び能力開発事業</b>(雇用保険二事業)を行うことができる。",
"a": true,
"exp": "〇。法3条。雇用保険二事業とは雇用安定事業及び能力開発事業をいう。",
"page": 13
},
{
"law": "総則",
"cat": "権限の委任",
"q": "雇用保険法に定める厚生労働大臣の権限は、その全部を都道府県労働局長に委任しなければならない。",
"a": false,
"exp": "×。法81条。委任できるのはその「一部」であり、また「委任することができる」のであって、全部を委任しなければならないわけではない。",
"page": 14
},
{
"law": "総則",
"cat": "諮問",
"q": "厚生労働大臣は、雇用保険法の施行に関する重要事項について決定しようとするときは、あらかじめ、<b>労働政策審議会</b>の意見を聴かなければならない。",
"a": true,
"exp": "〇。法72条。重要事項決定の際は、あらかじめ労働政策審議会の意見を聴かなければならない。",
"page": 15
},
{
"law": "総則",
"cat": "用語の定義",
"q": "「失業」とは、被保険者が離職し、労働の意思及び能力を有するにもかかわらず、職業に就くことができない状態にあることをいう。",
"a": true,
"exp": "〇。法4条3項。失業とは離職し労働の意思及び能力を有するにもかかわらず職業に就くことができない状態をいう。",
"page": 16
},
{
"law": "総則",
"cat": "用語の定義",
"q": "「離職」とは、被保険者について、事業主との雇用関係が終了することをいう。",
"a": true,
"exp": "〇。法4条2項。離職とは被保険者について事業主との雇用関係が終了することをいう。",
"page": 16
},
{
"law": "総則",
"cat": "賃金",
"q": "雇用保険法における賃金は、健康保険法等と同様に標準報酬制をとっている。",
"a": false,
"exp": "×。行政手引50401。雇用保険法は標準報酬制と異なり、賃金変動の実際に即した総賃金制(実賃金制)をとっている。",
"page": 17
},
{
"law": "適用・被保険者",
"cat": "適用事業",
"q": "雇用保険においては、労働者が雇用される事業を<b>適用事業</b>とする。",
"a": true,
"exp": "〇。法5条1項。労働者が雇用される事業を適用事業とする。",
"page": 20
},
{
"law": "適用・被保険者",
"cat": "暫定任意適用事業",
"q": "個人経営であって常時5人未満の労働者を雇用する農林・畜産・養蚕・水産の事業は、当分の間、暫定任意適用事業とされる。",
"a": true,
"exp": "〇。法附則2条1項。個人経営、農林等の事業、常時5人以上以外の事業のすべてを満たすものが暫定任意適用事業となる。",
"page": 21
},
{
"law": "適用・被保険者",
"cat": "暫定任意適用事業",
"q": "暫定任意適用事業の事業主が任意加入の申請をする場合、その事業に使用される労働者の<b>3分の1以上</b>の同意を得る必要がある。",
"a": false,
"exp": "×。法附則2条。同意が必要なのは労働者の「2分の1以上」である。",
"page": 21
},
{
"law": "適用・被保険者",
"cat": "適用事業所届出",
"q": "事業主は、事業所を設置したときは、その設置の日の翌日から起算して<b>10日以内</b>に、事業所の所在地を管轄する公共職業安定所の長に届け出なければならない。",
"a": true,
"exp": "〇。則141条1項。設置・廃止の日の翌日から起算して10日以内に届け出る。",
"page": 22
},
{
"law": "適用・被保険者",
"cat": "書類の保管",
"q": "事業主は、雇用保険に関する書類を原則としてその完結の日から2年間、被保険者に関する書類は4年間保管しなければならない。",
"a": true,
"exp": "〇。則143条。原則2年間、被保険者に関する書類は例外として4年間保管する。",
"page": 23
},
{
"law": "適用・被保険者",
"cat": "被保険者",
"q": "「被保険者」とは、適用事業に雇用される労働者であって、適用除外事由に該当する者以外のものをいう。",
"a": true,
"exp": "〇。法4条1項。適用事業に雇用される労働者で適用除外事由に該当しないものが被保険者である。",
"page": 24
},
{
"law": "適用・被保険者",
"cat": "被保険者の種類",
"q": "被保険者は、就労の実態に応じて、一般被保険者・高年齢被保険者・短期雇用特例被保険者・日雇労働被保険者の<b>4種類</b>に分けられる。",
"a": true,
"exp": "〇。行政手引20302。被保険者は4種類に分けられている。",
"page": 25
},
{
"law": "適用・被保険者",
"cat": "適用除外",
"q": "1週間の所定労働時間が<b>30時間未満</b>である者は、原則として被保険者とされない。",
"a": false,
"exp": "×。法6条。適用除外となるのは1週間の所定労働時間が「20時間未満」である者である。",
"page": 25
},
{
"law": "適用・被保険者",
"cat": "適用除外",
"q": "同一の事業主の適用事業に継続して<b>31日以上</b>雇用されることが見込まれない者は、原則として被保険者とされない。",
"a": true,
"exp": "〇。法6条。継続して31日以上雇用される見込みがない者は適用除外となる。ただし前2月各月18日以上雇用された者等は被保険者となる。",
"page": 26
},
{
"law": "適用・被保険者",
"cat": "具体例",
"q": "株式会社の代表取締役は、原則として被保険者となる。",
"a": false,
"exp": "×。行政手引。代表取締役は被保険者とならない。取締役であっても部長等従業員身分を有し労働者性が強い者に限り被保険者となり得る。",
"page": 29
},
{
"law": "適用・被保険者",
"cat": "具体例",
"q": "家事使用人は、原則として被保険者とならない。",
"a": true,
"exp": "〇。行政手引。家事使用人は被保険者とならない。ただし主として家事以外の労働に従事することを本務とする者は被保険者となる。",
"page": 29
},
{
"law": "適用・被保険者",
"cat": "具体例",
"q": "ワーキング・ホリデー制度による入国者は、被保険者とならない。",
"a": true,
"exp": "〇。行政手引。主として休暇を過ごす目的の入国で、付随的活動として就労が認められるものであることから被保険者とならない。",
"page": 31
},
{
"law": "適用・被保険者",
"cat": "高年齢被保険者",
"q": "高年齢被保険者とは、<b>60歳以上</b>の被保険者(短期雇用特例被保険者及び日雇労働被保険者に該当する者を除く)をいう。",
"a": false,
"exp": "×。法37条の2第1項。高年齢被保険者とは「65歳以上」の被保険者(短期雇用特例・日雇に該当する者を除く)をいう。",
"page": 32
},
{
"law": "適用・被保険者",
"cat": "高年齢被保険者の特例",
"q": "特例高年齢被保険者の申出ができるのは、2以上の事業主の適用事業に雇用される<b>65歳以上</b>の者であって、一の事業主の適用事業における1週間の所定労働時間が20時間未満であること等の要件に該当する者である。",
"a": true,
"exp": "〇。法37条の5第1項。2以上の事業主に雇用される65歳以上の者で所定の要件を満たす者が申出により高年齢被保険者となることができる。",
"page": 33
},
{
"law": "適用・被保険者",
"cat": "短期雇用特例被保険者",
"q": "短期雇用特例被保険者とは、季節的に雇用される者のうち、4か月以内の期間を定めて雇用される者及び1週間の所定労働時間が20時間以上30時間未満である者の<b>いずれにも該当しない者</b>をいう。",
"a": true,
"exp": "〇。法38条1項。季節的雇用者のうち、4か月以内期間雇用者及び20時間以上30時間未満の者のいずれにも該当しない者をいう。",
"page": 35
},
{
"law": "適用・被保険者",
"cat": "短期雇用特例被保険者",
"q": "短期雇用特例被保険者が同一事業主に引き続き<b>1年以上</b>雇用される場合には、一般被保険者等への被保険者資格の切替えが行われる。",
"a": true,
"exp": "〇。行政手引20451。1年以上雇用されるに至った日が切替日となる。",
"page": 35
},
{
"law": "適用・被保険者",
"cat": "日雇労働者",
"q": "日雇労働者とは、日々雇用される者又は<b>30日以内</b>の期間を定めて雇用される者をいう。",
"a": true,
"exp": "〇。法42条。日々雇用される者又は30日以内の期間を定めて雇用される者をいう。",
"page": 36
},
{
"law": "適用・被保険者",
"cat": "日雇労働被保険者",
"q": "日雇労働被保険者が前2月の各月において18日以上同一の事業主の適用事業に雇用された場合等において、公共職業安定所長の<b>資格継続の認可</b>を受けたときは、引き続き日雇労働被保険者となることができる。",
"a": true,
"exp": "〇。法43条2項。資格継続の認可を受けたときは引き続き日雇労働被保険者となることができる。",
"page": 36
},
{
"law": "適用・被保険者",
"cat": "届出",
"q": "事業主は、その雇用する労働者が被保険者となったときは、資格取得届を、事実のあった日の翌日から起算して<b>10日以内</b>に提出しなければならない。",
"a": false,
"exp": "×。則6条1項。資格取得届の提出期限は事実のあった日の属する月の「翌月10日まで」である。翌日から10日以内は資格喪失届である。",
"page": 39
},
{
"law": "適用・被保険者",
"cat": "届出",
"q": "事業主は、その雇用する労働者が被保険者でなくなったときは、資格喪失届を、事実のあった日の翌日から起算して<b>10日以内</b>に提出しなければならない。",
"a": true,
"exp": "〇。則7条1項。資格喪失届の提出期限は事実のあった日の翌日から起算して10日以内である。",
"page": 43
},
{
"law": "適用・被保険者",
"cat": "確認",
"q": "被保険者又は被保険者であった者は、いつでも、被保険者となったこと又はでなくなったことの確認を請求することができる。",
"a": true,
"exp": "〇。法8条。被保険者又は被保険者であった者はいつでも確認を請求することができる。",
"page": 41
},
{
"law": "適用・被保険者",
"cat": "離職証明書",
"q": "離職の日において<b>59歳以上</b>である被保険者については、被保険者が離職票の交付を希望しない場合であっても、離職証明書を添えなければならない。",
"a": true,
"exp": "〇。則7条3項。離職日において59歳以上の被保険者については交付希望がなくても離職証明書を添えなければならない。",
"page": 44
},
{
"law": "適用・被保険者",
"cat": "資格喪失日",
"q": "被保険者は、離職した日において、被保険者資格を喪失する。",
"a": false,
"exp": "×。行政手引20601。離職による資格喪失日は「離職した日の翌日」である。",
"page": 45
},
{
"law": "適用・被保険者",
"cat": "転勤届",
"q": "転勤前の事業所と転勤後の事業所が同じ公共職業安定所の管轄内にあるときは、転勤届の提出は必要ない。",
"a": false,
"exp": "×。則13条。同じ公共職業安定所の管轄内にあるときであっても転勤届の提出は必要である。",
"page": 48
},
{
"law": "通則",
"cat": "失業等給付",
"q": "失業等給付は、求職者給付、就職促進給付、教育訓練給付及び<b>雇用継続給付</b>とする。",
"a": true,
"exp": "〇。法10条1項。失業等給付は4種類で、求職者給付・就職促進給付・教育訓練給付・雇用継続給付である。",
"page": 56
},
{
"law": "通則",
"cat": "求職者給付",
"q": "高年齢被保険者に係る求職者給付は、<b>特例一時金</b>とされる。",
"a": false,
"exp": "×。法10条3項。高年齢被保険者に係る求職者給付は「高年齢求職者給付金」である。特例一時金は短期雇用特例被保険者に係るものである。",
"page": 56
},
{
"law": "通則",
"cat": "雇用継続給付",
"q": "雇用継続給付は、高年齢雇用継続給付、介護休業給付金及び育児休業給付金とする。",
"a": false,
"exp": "×。法10条6項。雇用継続給付は高年齢雇用継続給付及び介護休業給付金である。育児休業給付は雇用継続給付ではなく育児休業等給付に含まれる。",
"page": 57
},
{
"law": "通則",
"cat": "未支給の失業等給付",
"q": "未支給の失業等給付を請求できる遺族の範囲は、死亡した者の配偶者、子、父母、孫、祖父母又は兄弟姉妹であって、死亡当時その者と<b>生計を同じくしていたもの</b>である。",
"a": true,
"exp": "〇。法10条の3第1項。所定の遺族で死亡当時生計を同じくしていたものが請求できる。",
"page": 59
},
{
"law": "通則",
"cat": "未支給の失業等給付",
"q": "未支給の失業等給付を請求しようとする者は、受給資格者等が死亡した日の翌日から起算して<b>6か月以内</b>に請求書を提出しなければならない。",
"a": true,
"exp": "〇。則17条の2第1項。死亡日の翌日から起算して6か月以内に提出する。",
"page": 60
},
{
"law": "通則",
"cat": "返還命令等",
"q": "偽りその他不正の行為により失業等給付の支給を受けた者に対し、政府はその額の<b>2倍</b>に相当する額以下の金額の納付を命ずることができる。",
"a": true,
"exp": "〇。法10条の4第1項。不正受給した失業等給付の額の2倍に相当する額以下の金額の納付を命ずることができる。",
"page": 61
},
{
"law": "通則",
"cat": "受給権の保護",
"q": "失業等給付を受ける権利は、譲り渡し、担保に供し、又は差し押さえることができない。",
"a": true,
"exp": "〇。法11条。失業等給付の受給権は譲渡・担保供与・差押えができない。",
"page": 63
},
{
"law": "通則",
"cat": "公課の禁止",
"q": "租税その他の公課は、失業等給付として支給を受けた金銭を標準として課することができない。",
"a": true,
"exp": "〇。法12条。失業等給付として支給を受けた金銭を標準として公課を課すことはできない。",
"page": 63
},
{
"law": "求職者給付(基本手当)",
"cat": "受給資格",
"q": "基本手当は、原則として離職日以前2年間に被保険者期間が通算して<b>12か月以上</b>あるときに支給される。",
"a": true,
"exp": "〇。法13条1項。原則として算定対象期間2年間に被保険者期間が通算12か月以上必要である。",
"page": 67
},
{
"law": "求職者給付(基本手当)",
"cat": "受給資格",
"q": "特定理由離職者又は特定受給資格者は、離職日以前1年間に被保険者期間が通算して<b>6か月以上</b>あれば受給資格を得ることができる。",
"a": true,
"exp": "〇。法13条2項。特定理由離職者・特定受給資格者は1年間に被保険者期間6か月以上で受給資格を得る。",
"page": 67
},
{
"law": "求職者給付(基本手当)",
"cat": "特定受給資格者",
"q": "<b>定年</b>により離職した者は、特定受給資格者となる。",
"a": false,
"exp": "×。法23条。定年により離職した者は特定受給資格者とならない。",
"page": 68
},
{
"law": "求職者給付(基本手当)",
"cat": "受給要件の緩和",
"q": "疾病等により引き続き<b>30日以上</b>賃金の支払を受けることができなかった被保険者については、その日数を算定対象期間に加えることができるが、加算後の期間が4年を超えるときは4年間が限度となる。",
"a": true,
"exp": "〇。法13条1項。引き続き30日以上賃金を受けられなかった日数を加算するが、加算した期間が4年を超えるときは4年間が限度となる。",
"page": 72
},
{
"law": "求職者給付(基本手当)",
"cat": "被保険者期間",
"q": "被保険者期間は、被保険者であった期間のうち、賃金の支払の基礎となった日数が<b>11日以上</b>あるものを1か月として計算する。",
"a": true,
"exp": "〇。法14条1項。喪失応当日からさかのぼった各期間のうち賃金支払基礎日数が11日以上あるものを1か月として計算する。",
"page": 74
},
{
"law": "求職者給付(基本手当)",
"cat": "被保険者期間",
"q": "被保険者期間が12か月又は6か月に満たない場合、区切られた期間のうち賃金支払基礎日数が11日以上又は賃金の支払の基礎となった時間数が<b>80時間以上</b>のものは1か月又は2分の1か月として計算する。",
"a": true,
"exp": "〇。法14条3項。11日以上又は80時間以上のいずれかに該当するものを1か月又は2分の1か月として計算する。",
"page": 74
},
{
"law": "求職者給付(基本手当)",
"cat": "待期",
"q": "基本手当は、離職後最初に公共職業安定所に出頭し求職の申込みをした日以後において、失業している日が通算して<b>7日</b>に満たない間は支給されない。",
"a": true,
"exp": "〇。法21条。求職の申込みをした日以後、失業している日が通算して7日に満たない間は支給されない(待期)。",
"page": 88
},
{
"law": "求職者給付(基本手当)",
"cat": "待期",
"q": "待期は、一の受給期間内に2回をもって足りる。",
"a": false,
"exp": "×。待期は一の受給期間内に「1回」をもって足りる。すでに待期を満了している者は再び要求されない。",
"page": 88
},
{
"law": "求職者給付(基本手当)",
"cat": "失業の認定",
"q": "失業の認定は、求職の申込みを受けた公共職業安定所において、離職後最初に出頭した日から起算して<b>4週間に1回</b>ずつ直前の28日の各日について行う。",
"a": true,
"exp": "〇。則22条等。原則として4週間に1回ずつ、直前の28日の各日について失業の認定を行う。",
"page": 85
},
{
"law": "求職者給付(基本手当)",
"cat": "失業の認定",
"q": "公共職業安定所長の指示した公共職業訓練等を受ける受給資格者に係る失業の認定は、<b>1か月に1回</b>行う。",
"a": true,
"exp": "〇。法15条3項。公共職業訓練等を受ける受給資格者については1か月に1回、直前の月の各日について行う。",
"page": 85
},
{
"law": "求職者給付(基本手当)",
"cat": "失業の認定",
"q": "疾病又は負傷のために公共職業安定所に出頭できなかった場合、その期間が継続して<b>15日未満</b>であるときは、証明書を提出することによって失業の認定を受けることができる。",
"a": true,
"exp": "〇。法15条4項。疾病・負傷で出頭できず継続15日未満のときは証明書による認定を受けられる。",
"page": 86
},
{
"law": "求職者給付(基本手当)",
"cat": "失業の認定",
"q": "代理人による失業の認定は、原則として認められる。",
"a": false,
"exp": "×。行政手引51252。代理人による失業の認定は原則として認められない。公共職業訓練等の訓練施設入所中の者等は例外として認められる。",
"page": 85
},
{
"law": "求職者給付(基本手当)",
"cat": "支給方法",
"q": "基本手当は、原則として受給資格者の<b>預金又は貯金への振込み</b>の方法により支給する。",
"a": true,
"exp": "〇。則44条。基本手当は原則として預金又は貯金への振込みの方法により支給する。",
"page": 89
},
{
"law": "求職者給付(賃金日額等)",
"cat": "賃金日額",
"q": "賃金日額は、被保険者期間として計算された最後の<b>6か月間</b>に支払われた賃金の総額を<b>180</b>で除して得た額とする。",
"a": true,
"exp": "〇。法17条1項。最後の6か月間に支払われた賃金の総額を180で除して得た額が原則の賃金日額である。",
"page": 90
},
{
"law": "求職者給付(賃金日額等)",
"cat": "賃金日額",
"q": "賃金日額の算定では、臨時に支払われる賃金及び<b>3か月を超える期間ごと</b>に支払われる賃金は除かれる。",
"a": true,
"exp": "〇。法17条1項。臨時に支払われる賃金及び3か月を超える期間ごとに支払われる賃金は賃金日額の算定から除かれる。",
"page": 90
},
{
"law": "求職者給付(賃金日額等)",
"cat": "賃金日額",
"q": "賃金日額の下限額は、年齢区分に応じて異なる額が定められている。",
"a": false,
"exp": "×。法17条4項。賃金日額の下限額は年齢にかかわらず一律の額(3,014円)である。上限額が年齢区分に応じて異なる。",
"page": 94
},
{
"law": "求職者給付(賃金日額等)",
"cat": "基本手当の日額",
"q": "基本手当の日額は、賃金日額に給付率を乗じて算定し、給付率は離職日に60歳未満の者については100分の80から100分の50までの範囲で決定される。",
"a": true,
"exp": "〇。法16条。60歳未満は100分の80から50まで、60歳以上65歳未満は100分の80から45までの範囲で決定される。",
"page": 95
},
{
"law": "求職者給付(賃金日額等)",
"cat": "基本手当の日額",
"q": "基本手当の給付率は、離職日に60歳以上65歳未満である受給資格者については、100分の80から<b>100分の45</b>までの範囲で決定される。",
"a": true,
"exp": "〇。法16条。60歳以上65歳未満の給付率の下限は100分の45である。",
"page": 95
},
{
"law": "求職者給付(賃金日額等)",
"cat": "基本手当の減額",
"q": "失業の認定に係る期間中に自己の労働によって収入を得た場合、収入の1日分から控除額を控除した額と基本手当の日額の合計額が賃金日額の<b>100分の80</b>に相当する額を超えないときは、基本手当は全額支給される。",
"a": true,
"exp": "〇。法19条1項。合計額が賃金日額の100分の80に相当する額を超えないときは調整は行われず全額支給される。",
"page": 97
},
{
"law": "求職者給付(所定給付日数)",
"cat": "所定給付日数",
"q": "所定給付日数とは、一の受給資格に基づき基本手当を支給する日数の上限である。",
"a": true,
"exp": "〇。法22条等。所定給付日数とは一の受給資格に基づき基本手当を支給する日数の上限である。",
"page": 100
},
{
"law": "求職者給付(所定給付日数)",
"cat": "所定給付日数",
"q": "一般の受給資格者の所定給付日数は、算定基礎期間が10年未満の場合、年齢にかかわらず一律<b>90日</b>である。",
"a": true,
"exp": "〇。法22条。一般の受給資格者は算定基礎期間10年未満で90日、10年以上20年未満で120日、20年以上で150日である。",
"page": 100
},
{
"law": "求職者給付(所定給付日数)",
"cat": "所定給付日数",
"q": "就職が困難な者である受給資格者で算定基礎期間が1年以上であって離職日における年齢が45歳以上65歳未満の者の所定給付日数は、<b>360日</b>である。",
"a": true,
"exp": "〇。法22条2項。就職困難者で1年以上、45歳以上65歳未満の者は360日、45歳未満の者は300日である。",
"page": 100
},
{
"law": "求職者給付(所定給付日数)",
"cat": "就職が困難な者",
"q": "「就職が困難な者」であるか否かは、受給資格決定後にその状態が生じた者も含めて判断される。",
"a": false,
"exp": "×。法22条。就職が困難な者は受給資格決定時においていずれかに該当する状態にある者をいい、決定後に生じた者は含めない。",
"page": 101
},
{
"law": "求職者給付(所定給付日数)",
"cat": "算定基礎期間",
"q": "算定基礎期間は、原則として、受給資格者が基準日まで引き続いて同一の事業主の適用事業に被保険者として雇用された期間とする。",
"a": true,
"exp": "〇。法22条3項。算定基礎期間は原則として基準日まで引き続いて同一事業主の適用事業に雇用された期間である。",
"page": 102
},
{
"law": "求職者給付(受給期間)",
"cat": "受給期間",
"q": "基本手当は、原則として、一般の受給資格者については基準日の翌日から起算して<b>1年</b>の受給期間内の失業している日について支給される。",
"a": true,
"exp": "〇。法20条1項。一般の受給資格者の受給期間は基準日の翌日から起算して1年である。",
"page": 104
},
{
"law": "求職者給付(受給期間)",
"cat": "受給期間",
"q": "基準日において45歳以上65歳未満であって算定基礎期間が1年以上の就職が困難な者(所定給付日数360日)である受給資格者の受給期間は、基準日の翌日から起算して<b>1年に60日を加えた期間</b>である。",
"a": true,
"exp": "〇。法20条1項。所定給付日数360日の者は1年に60日を加えた期間が受給期間となる。",
"page": 104
},
{
"law": "求職者給付(受給期間)",
"cat": "受給期間の延長",
"q": "妊娠、出産、育児その他の理由により引き続き<b>30日以上</b>職業に就くことができない者は、申出によって受給期間を最高4年まで延長することができる。",
"a": true,
"exp": "〇。法20条1項。引き続き30日以上職業に就けない者はその日数を加算し最高4年まで延長できる。",
"page": 105
},
{
"law": "求職者給付(受給期間)",
"cat": "受給期間の延長",
"q": "60歳以上の定年退職等による受給期間の延長の申出は、離職の日の翌日から起算して<b>2か月以内</b>にしなければならない。",
"a": true,
"exp": "〇。則31条の3。定年退職等による延長の申出は離職日の翌日から起算して2か月以内に行う。",
"page": 106
},
{
"law": "求職者給付(延長給付)",
"cat": "訓練延長給付",
"q": "公共職業訓練等を受けるために待期している期間については、公共職業訓練等を受け始める日の前日までの引き続く<b>90日間</b>を限度に延長することができる。",
"a": true,
"exp": "〇。法24条等。待期している期間は引き続く90日間を限度に訓練延長給付が行われる。",
"page": 110
},
{
"law": "求職者給付(延長給付)",
"cat": "広域延長給付",
"q": "広域延長給付の延長日数は、<b>90日</b>が限度となる。",
"a": true,
"exp": "〇。法25条。広域延長給付の延長日数は90日が限度である。",
"page": 113
},
{
"law": "求職者給付(延長給付)",
"cat": "全国延長給付",
"q": "全国延長給付は、特定受給資格者のみを対象として実施される。",
"a": false,
"exp": "×。法27条。全国延長給付はすべての受給資格者を対象として実施される。延長日数は90日が限度である。",
"page": 114
},
{
"law": "求職者給付(延長給付)",
"cat": "延長給付の調整",
"q": "複数の延長給付の要件を満たした場合、個別延長給付、広域延長給付、全国延長給付、<b>訓練延長給付</b>の順序で行われる。",
"a": true,
"exp": "〇。法28条。個別→広域→全国→訓練延長給付の順序で行われる。",
"page": 115
},
{
"law": "求職者給付(延長給付)",
"cat": "地域延長給付",
"q": "地域延長給付は、個別延長給付と同じ順位とされ、広域延長給付や全国延長給付、訓練延長給付に優先する。",
"a": true,
"exp": "〇。法附則5条4項。地域延長給付は個別延長給付と同じ順位とされ、他の延長給付に優先する。",
"page": 115
},
{
"law": "求職者給付(給付制限)",
"cat": "職業紹介の拒否",
"q": "受給資格者が公共職業安定所の紹介する職業に就くことを拒んだときは、その拒んだ日から起算して<b>1か月間</b>は基本手当が支給されない。",
"a": true,
"exp": "〇。法32条1項。職業紹介・訓練受講の拒否による給付制限期間は1か月間である。",
"page": 117
},
{
"law": "求職者給付(給付制限)",
"cat": "離職理由による給付制限",
"q": "被保険者が自己の責めに帰すべき重大な理由によって解雇され、又は正当な理由がなく自己の都合によって退職したときは、待期期間の満了後<b>1か月以上3か月以内</b>の間で公共職業安定所長の定める期間、基本手当が支給されない。",
"a": true,
"exp": "〇。法33条1項。離職理由による給付制限期間は待期満了後1か月以上3か月以内である。",
"page": 118
},
{
"law": "求職者給付(給付制限)",
"cat": "離職理由による給付制限",
"q": "正当な理由がない自己都合により退職した場合、原則として給付制限期間は<b>1か月</b>となる。",
"a": true,
"exp": "〇。行政手引52205。正当な理由がない自己都合退職の給付制限期間は原則1か月となる。5年間に2回以上の場合は3か月となる。",
"page": 119
},
{
"law": "求職者給付(給付制限)",
"cat": "不正受給による給付制限",
"q": "偽りその他不正の行為により求職者給付又は就職促進給付の支給を受け、又は受けようとした者には、その日以後、原則として基本手当は支給されない。",
"a": true,
"exp": "〇。法34条。不正受給による給付制限により、原則としてその日以後基本手当は支給されない。",
"page": 121
},
{
"law": "求職者給付(その他)",
"cat": "傷病手当",
"q": "傷病手当は、受給資格者が求職の申込みをした後において、疾病又は負傷のために継続して<b>15日以上</b>職業に就くことができない場合に支給される。",
"a": true,
"exp": "〇。法37条1項。求職の申込み後、疾病・負傷で継続15日以上職業に就けない場合に傷病手当が支給される。",
"page": 122
},
{
"law": "求職者給付(その他)",
"cat": "傷病手当",
"q": "傷病手当の日額は、基本手当の日額の<b>100分の80</b>に相当する額である。",
"a": false,
"exp": "×。法37条3項。傷病手当の日額は基本手当の日額に相当する額である。",
"page": 123
},
{
"law": "求職者給付(その他)",
"cat": "受講手当",
"q": "受講手当は、公共職業訓練等を受けた日について、<b>30日分</b>を限度として支給され、支給額は日額500円である。",
"a": false,
"exp": "×。則57条。受講手当は「40日分」を限度として支給される。支給額は日額500円である。",
"page": 126
},
{
"law": "求職者給付(その他)",
"cat": "通所手当",
"q": "通所手当は、月額<b>42,500円</b>を限度に、通所方法に応じて算定した額が支給される。",
"a": true,
"exp": "〇。則59条。通所手当は月額42,500円を限度に通所方法に応じて算定した額が支給される。",
"page": 126
},
{
"law": "求職者給付(その他)",
"cat": "寄宿手当",
"q": "寄宿手当の支給額は、月額<b>10,400円</b>である。",
"a": false,
"exp": "×。則60条2項。寄宿手当の支給額は月額「10,700円」である。年齢や被保険者期間により異なることはない。",
"page": 128
},
{
"law": "高年齢・短期・日雇",
"cat": "高年齢求職者給付金",
"q": "高年齢求職者給付金は、原則として離職の日以前<b>1年間</b>に被保険者期間が通算して6か月以上あるときに支給される。",
"a": true,
"exp": "〇。法37条の3第1項。高年齢求職者給付金は原則として離職日以前1年間に被保険者期間6か月以上で支給される。",
"page": 132
},
{
"law": "高年齢・短期・日雇",
"cat": "高年齢求職者給付金",
"q": "高年齢求職者給付金の支給額は、算定基礎期間が1年未満の場合は基本手当の日額の30日分、1年以上の場合は<b>40日分</b>である。",
"a": false,
"exp": "×。法37条の4。算定基礎期間1年未満で30日分、1年以上で「50日分」である。",
"page": 134
},
{
"law": "高年齢・短期・日雇",
"cat": "高年齢求職者給付金",
"q": "高年齢求職者給付金の基本手当の日額は、<b>30歳未満</b>である受給資格者に係る給付率を用いて算定する。",
"a": true,
"exp": "〇。法37条の4等。基本手当の日額は30歳未満の受給資格者に係る給付率(100分の50から80)を用いて算定する。",
"page": 134
},
{
"law": "高年齢・短期・日雇",
"cat": "高年齢求職者給付金",
"q": "高年齢求職者給付金は、傷病等により引き続き30日以上職業に就くことができない場合には、受給期限の延長が認められる。",
"a": false,
"exp": "×。行政手引54131。高年齢求職者給付金及び特例一時金は、傷病等による受給期限の延長は認められない。",
"page": 134
},
{
"law": "高年齢・短期・日雇",
"cat": "特例一時金",
"q": "特例一時金の額は、原則として基本手当の日額の30日分とされているが、当分の間、<b>40日分</b>とされている。",
"a": true,
"exp": "〇。法40条1項、附則8条。原則30日分だが暫定措置により当分の間40日分とされている。",
"page": 141
},
{
"law": "高年齢・短期・日雇",
"cat": "特例一時金",
"q": "特例一時金の受給期限は、離職の日の翌日から起算して<b>6か月</b>を経過する日までである。",
"a": true,
"exp": "〇。法39条2項。特例一時金の受給期限は離職日の翌日から起算して6か月を経過する日までである。",
"page": 141
},
{
"law": "高年齢・短期・日雇",
"cat": "特例一時金",
"q": "特例受給資格者が自己の労働により収入を得た場合、特例一時金は減額される。",
"a": false,
"exp": "×。行政手引55357。特例受給資格者が自己の労働により収入を得た場合でも、特例一時金は減額されない。",
"page": 141
},
{
"law": "高年齢・短期・日雇",
"cat": "日雇労働求職者給付金",
"q": "日雇労働求職者給付金(普通給付)は、その失業の日の属する月の前2月間に印紙保険料が通算して<b>26日分以上</b>納付されているときに支給される。",
"a": true,
"exp": "〇。法45条。普通給付は前2月間に印紙保険料が通算26日分以上納付されているときに支給される。",
"page": 146
},
{
"law": "高年齢・短期・日雇",
"cat": "日雇労働求職者給付金",
"q": "日雇労働求職者給付金の特例給付は、継続する6月間に印紙保険料が各月11日分以上、かつ通算して<b>78日分以上</b>納付されていること等の要件に該当するときに支給される。",
"a": true,
"exp": "〇。法53条。特例給付は継続6月間に各月11日分以上かつ通算78日分以上の納付等の要件に該当するときに支給される。",
"page": 147
},
{
"law": "高年齢・短期・日雇",
"cat": "日雇労働求職者給付金",
"q": "日雇労働求職者給付金は、各週につき日雇労働被保険者が職業に就かなかった最初の日については支給されない。",
"a": true,
"exp": "〇。法50条2項。各週につき職業に就かなかった最初の1日(不就労日)については支給されない。",
"page": 149
},
{
"law": "高年齢・短期・日雇",
"cat": "日雇労働求職者給付金",
"q": "日雇労働求職者給付金の特例給付は、基礎期間の最後の月の翌月以後4月の期間内の失業している日について、通算して<b>60日分</b>を限度として支給される。",
"a": true,
"exp": "〇。法54条。特例給付は4月の期間内の失業している日について通算60日分を限度として支給される。",
"page": 150
},
{
"law": "高年齢・短期・日雇",
"cat": "日雇労働求職者給付金の日額",
"q": "日雇労働求職者給付金の日額の第1級給付金は、<b>6,200円</b>である。",
"a": false,
"exp": "×。法48条。第1級給付金は「7,500円」である。6,200円は第2級給付金、4,100円は第3級給付金である。",
"page": 151
},
{
"law": "就職促進給付",
"cat": "就業促進手当",
"q": "就業促進手当は、再就職手当、就業促進定着手当及び<b>常用就職支度手当</b>とする。",
"a": true,
"exp": "〇。法56条の3等。就業促進手当は再就職手当、就業促進定着手当、常用就職支度手当の3種類である。",
"page": 156
},
{
"law": "就職促進給付",
"cat": "再就職手当",
"q": "再就職手当は、安定した職業に就いた日の前日における基本手当の支給残日数が当該受給資格に基づく所定給付日数の<b>3分の1以上</b>ある受給資格者が所定の要件に該当するときに支給される。",
"a": true,
"exp": "〇。法56条の3第1項。支給残日数が所定給付日数の3分の1以上ある者が要件に該当するときに支給される。",
"page": 157
},
{
"law": "就職促進給付",
"cat": "再就職手当",
"q": "再就職手当の額は、支給残日数が所定給付日数の3分の2以上のときは、基本手当日額に支給残日数を乗じた額の<b>10分の6</b>に相当する額である。",
"a": false,
"exp": "×。法56条の3第3項。支給残日数3分の2以上のときは「10分の7」を乗じる。3分の1以上3分の2未満が10分の6である。",
"page": 158
},
{
"law": "就職促進給付",
"cat": "給付の調整",
"q": "受給資格者が安定した職業に就いた日前<b>3年以内</b>の就職について再就職手当又は常用就職支度手当の支給を受けたことがある場合には、再就職手当は支給されない。",
"a": true,
"exp": "〇。法56条の3第2項。3年以内に再就職手当等を受けたことがある場合は支給されない。",
"page": 157
},
{
"law": "就職促進給付",
"cat": "就業促進定着手当",
"q": "就業促進定着手当は、再就職手当の支給を受けた者が、同一事業主の適用事業にその職業に就いた日から引き続いて<b>6か月以上</b>雇用され、みなし賃金日額が算定基礎賃金日額を下回るときに支給される。",
"a": true,
"exp": "〇。法56条の3第3項。再就職後6か月以上雇用され賃金が低下した場合に追加的に支給される。",
"page": 161
},
{
"law": "就職促進給付",
"cat": "常用就職支度手当",
"q": "常用就職支度手当の支給対象となる「就職が困難な者」の範囲は、基本手当の所定給付日数について規定する「就職が困難な者」より<b>広い</b>。",
"a": true,
"exp": "〇。則82条の3。常用就職支度手当の就職困難者の範囲は所定給付日数の就職困難者より広い。",
"page": 164
},
{
"law": "就職促進給付",
"cat": "移転費",
"q": "移転費は、鉄道賃、船賃、航空賃、車賃及び移転料の<b>5種類</b>とされている。",
"a": false,
"exp": "×。則87条。移転費は鉄道賃・船賃・航空賃・車賃・移転料・着後手当の「6種類」である。",
"page": 166
},
{
"law": "就職促進給付",
"cat": "移転費",
"q": "移転費の支給を受けた受給資格者等が、紹介された職業に就かなかったとき等は、その事実が確定した日の翌日から起算して<b>10日以内</b>に届け出るとともに、移転費に相当する額を返還しなければならない。",
"a": true,
"exp": "〇。則95条1項。紹介された職業に就かなかったとき等は10日以内に届け出て返還しなければならない。",
"page": 167
},
{
"law": "就職促進給付",
"cat": "短期訓練受講費",
"q": "短期訓練受講費の額は、教育訓練の受講のために支払った費用の額に<b>100分の20</b>を乗じて得た額(その額が10万円を超えるときは10万円)とされている。",
"a": true,
"exp": "〇。則100条の3。支払った費用の額に100分の20を乗じた額(上限10万円)が支給される。",
"page": 170
},
{
"law": "教育訓練給付",
"cat": "教育訓練給付金",
"q": "教育訓練給付金は、原則として支給要件期間が<b>3年以上</b>であるときに支給される。",
"a": true,
"exp": "〇。法60条の2第1項。原則として支給要件期間が3年以上であるときに支給される。",
"page": 176
},
{
"law": "教育訓練給付",
"cat": "教育訓練給付金",
"q": "基準日前に教育訓練給付金の支給を受けたことのない者の場合、専門実践教育訓練に係る支給要件期間は<b>2年以上</b>でよい。",
"a": true,
"exp": "〇。法60条の2第1項等。給付金を受けたことのない者は、一般・特定一般は1年以上、専門実践は2年以上でよい。",
"page": 179
},
{
"law": "教育訓練給付",
"cat": "教育訓練給付金",
"q": "短期雇用特例被保険者及び日雇労働被保険者は、教育訓練給付金の支給対象とならない。",
"a": true,
"exp": "〇。法60条の2。短期雇用特例被保険者及び日雇労働被保険者は支給対象とならない。ただし離職後一定期間内の者は要件を満たせば支給を受けられる。",
"page": 177
},
{
"law": "教育訓練給付",
"cat": "支給率",
"q": "一般教育訓練を受け、修了した者に係る教育訓練給付金の支給率は、<b>100分の40</b>である。",
"a": false,
"exp": "×。則。一般教育訓練を修了した者の支給率は「100分の20」である。100分の40は特定一般教育訓練を修了した者の支給率である。",
"page": 182
},
{
"law": "教育訓練給付",
"cat": "支給率",
"q": "専門実践教育訓練を受け、修了した者(資格取得等・雇用なし)に係る支給率は、<b>100分の70</b>である。",
"a": false,
"exp": "×。則。専門実践教育訓練を受け修了した者(資格取得等・雇用に至らない者)の支給率は100分の50である。資格取得等し雇用された者は100分の70となる。",
"page": 182
},
{
"law": "教育訓練給付",
"cat": "上限額",
"q": "一般教育訓練を受け修了した者に係る教育訓練給付金の支給総額の上限額は、<b>10万円</b>である。",
"a": true,
"exp": "〇。則。一般教育訓練(支給率100分の20)に係る支給総額の上限額は10万円である。",
"page": 184
},
{
"law": "教育訓練給付",
"cat": "不支給",
"q": "教育訓練給付金の額として算定された額が<b>4,000円</b>を超えないときは、教育訓練給付金は支給されない。",
"a": true,
"exp": "〇。法60条の2第5項。算定額が4,000円を超えないときは支給されない。",
"page": 188
},
{
"law": "教育訓練給付",
"cat": "不支給",
"q": "教育訓練給付金支給対象者が基準日前<b>3年</b>の期間内に教育訓練給付金の支給を受けたことがあるときは、支給されない。",
"a": true,
"exp": "〇。法60条の2第5項。基準日前3年の期間内に教育訓練給付金を受けたことがあるときは支給されない。",
"page": 188
},
{
"law": "教育訓練給付",
"cat": "申請",
"q": "一般教育訓練に係る教育訓練給付金の支給申請は、一般教育訓練を修了した日の翌日から起算して<b>1か月以内</b>に行わなければならない。",
"a": true,
"exp": "〇。則101条の2の11。一般教育訓練修了日の翌日から起算して1か月以内に支給申請する。",
"page": 188
},
{
"law": "教育訓練給付",
"cat": "教育訓練休暇給付金",
"q": "教育訓練休暇給付金は、一般被保険者が職業に関する教育訓練を受けるための休暇を取得した場合に支給され、その教育訓練休暇は当該休暇の期間が<b>30日以上</b>であることが必要である。",
"a": true,
"exp": "〇。法60条の3、則。教育訓練休暇は当該休暇の期間が30日以上であり所定の訓練を受けるものであること等が要件である。",
"page": 192
},
{
"law": "教育訓練給付",
"cat": "教育訓練休暇給付金",
"q": "教育訓練休暇給付金の日額は、基本手当の日額に相当する額の<b>100分の60</b>に相当する額である。",
"a": false,
"exp": "×。法60条の3第5項。教育訓練休暇給付金の日額は基本手当の日額に相当する額である。100分の60を乗じるのは教育訓練支援給付金である。",
"page": 194
},
{
"law": "教育訓練給付",
"cat": "教育訓練支援給付金",
"q": "教育訓練支援給付金は、専門実践教育訓練を開始した日における年齢が<b>45歳未満</b>であること等の要件に該当する場合に支給される。",
"a": true,
"exp": "〇。法附則11条の2。教育訓練を開始した日における年齢が45歳未満であること等が要件である。",
"page": 196
},
{
"law": "教育訓練給付",
"cat": "教育訓練支援給付金",
"q": "教育訓練支援給付金の支給日額は、基本手当の日額に相当する額に<b>100分の60</b>を乗じて得た額である。",
"a": true,
"exp": "〇。法附則11条の2第3項。支給日額は基本手当の日額に相当する額に100分の60を乗じて得た額である。",
"page": 197
},
{
"law": "雇用継続給付(高年齢)",
"cat": "高年齢雇用継続基本給付金",
"q": "高年齢雇用継続基本給付金は、支給対象月に支払われた賃金の額が、みなし賃金日額に30を乗じて得た額の<b>100分の75</b>に相当する額を下るに至った場合に支給される。",
"a": true,
"exp": "〇。法61条1項。賃金が60歳到達時等の100分の75に相当する額を下る場合に支給される。",
"page": 203
},
{
"law": "雇用継続給付(高年齢)",
"cat": "高年齢雇用継続基本給付金",
"q": "高年齢雇用継続基本給付金は、被保険者が60歳に達した日後において、算定基礎期間に相当する期間が<b>5年</b>に満たないときは支給されない。",
"a": true,
"exp": "〇。法61条1項。算定基礎期間に相当する期間が5年に満たないときは支給されない。",
"page": 203
},
{
"law": "雇用継続給付(高年齢)",
"cat": "高年齢雇用継続基本給付金",
"q": "高年齢雇用継続基本給付金の額は、支給対象月の賃金額が「みなし賃金日額×30」の額の100分の64未満である場合、支給対象月の賃金額の<b>100分の10</b>に相当する額である。",
"a": false,
"exp": "×。法61条5項。100分の64未満の場合の支給率は100分の15である。",
"page": 205
},
{
"law": "雇用継続給付(高年齢)",
"cat": "高年齢再就職給付金",
"q": "高年齢再就職給付金は、受給資格に係る離職日における算定基礎期間が5年以上あり、かつ当該受給資格に基づく基本手当の支給を受けたことがあること等の要件に該当するときに支給される。",
"a": true,
"exp": "〇。法61条の2第1項。算定基礎期間5年以上、基本手当の支給を受けたこと等が要件である。",
"page": 208
},
{
"law": "雇用継続給付(高年齢)",
"cat": "高年齢再就職給付金",
"q": "高年齢再就職給付金は、就職日の前日における当該基本手当の支給残日数が、<b>50日未満</b>であるときは支給されない。",
"a": false,
"exp": "×。法61条の2。高年齢再就職給付金は支給残日数が「100日未満」であるときは支給されない。",
"page": 208
},
{
"law": "雇用継続給付(高年齢)",
"cat": "高年齢再就職給付金",
"q": "再就職後の支給対象月は、就職日の前日における基本手当の支給残日数が200日以上の場合、就職日の属する月から就職日の翌日から起算して<b>2年</b>を経過する日の属する月までの期間内にある月である。",
"a": true,
"exp": "〇。法61条の2第2項。支給残日数200日以上は2年、200日未満は1年を経過する日の属する月までである。",
"page": 209
},
{
"law": "雇用継続給付(高年齢)",
"cat": "支給調整",
"q": "高年齢再就職給付金の支給を受けることができる者が、同一の就職につき再就職手当の支給を受けたときは、高年齢再就職給付金は支給されない。",
"a": true,
"exp": "〇。法61条の2第4項。再就職手当を受けたときは高年齢再就職給付金を支給せず、いずれを受けるかは本人が選択する。",
"page": 210
},
{
"law": "雇用継続給付(介護)",
"cat": "介護休業給付金",
"q": "介護休業給付金は、原則として介護休業を開始した日前<b>2年間</b>に、みなし被保険者期間が通算して12か月以上あること等が要件である。",
"a": true,
"exp": "〇。法61条の4第1項。介護休業開始日前2年間にみなし被保険者期間が通算12か月以上必要である。",
"page": 212
},
{
"law": "雇用継続給付(介護)",
"cat": "対象家族",
"q": "介護休業給付金の対象家族には、被保険者の配偶者、父母、子、祖父母、兄弟姉妹、孫及び<b>配偶者の父母</b>が含まれる。",
"a": true,
"exp": "〇。法61条の4第1項、則101条の17。配偶者の父母も対象家族に含まれる。",
"page": 213
},
{
"law": "雇用継続給付(介護)",
"cat": "介護休業給付金",
"q": "介護休業給付金の額は、当分の間、休業開始時賃金日額に支給日数を乗じて得た額の<b>100分の67</b>に相当する額とされている。",
"a": true,
"exp": "〇。法61条の4第4項、附則12条。原則100分の40だが当分の間100分の67とされている。",
"page": 215
},
{
"law": "雇用継続給付(介護)",
"cat": "介護休業の分割取得",
"q": "同一の対象家族について、被保険者がした介護休業の日数を合算して得た日数が<b>93日</b>に達した日後の介護休業については、介護休業給付金は支給されない。",
"a": true,
"exp": "〇。法61条の4第6項。合算日数が93日に達した日後の介護休業及び4回目以後の介護休業は支給されない。",
"page": 214
},
{
"law": "雇用継続給付(介護)",
"cat": "介護休業の分割取得",
"q": "同一の対象家族について被保険者が<b>4回以上</b>の介護休業をした場合における4回目以後の介護休業については、介護休業給付金は支給されない。",
"a": true,
"exp": "〇。法61条の4第6項。4回目以後の介護休業については支給されない。",
"page": 214
},
{
"law": "雇用継続給付(介護)",
"cat": "支給申請",
"q": "介護休業給付金の支給申請は、介護休業を<b>開始した日</b>の翌日から起算して2か月を経過する日の属する月の末日までに行わなければならない。",
"a": false,
"exp": "×。則101条の19。介護休業給付金の支給申請は介護休業を「終了した日」の翌日から起算して2か月を経過する日の属する月の末日までに行う。",
"page": 217
},
{
"law": "育児休業給付",
"cat": "育児休業給付金",
"q": "育児休業給付金は、原則として育児休業を開始した日前2年間に、みなし被保険者期間が通算して<b>12か月以上</b>あること等が要件である。",
"a": true,
"exp": "〇。法61条の7第1項。育児休業開始日前2年間にみなし被保険者期間が通算12か月以上必要である。",
"page": 221
},
{
"law": "育児休業給付",
"cat": "育児休業給付金",
"q": "育児休業給付金の額は、休業開始時賃金日額に支給日数を乗じて得た額の100分の50に相当する額であるが、休業日数が通算して<b>180日</b>に達するまでの間に限り100分の67に相当する額である。",
"a": true,
"exp": "〇。法61条の7第6項。休業日数180日まで100分の67、181日以降100分の50である。",
"page": 228
},
{
"law": "育児休業給付",
"cat": "育児休業給付金",
"q": "育児休業の分割取得において、被保険者が同一の子について<b>3回以上</b>の育児休業をした場合における3回目以後の育児休業については、育児休業給付金は支給されない。",
"a": true,
"exp": "〇。法61条の7第2項。同一の子について3回以上の育児休業をした場合の3回目以後の育児休業は支給されない(所定の場合を除く)。",
"page": 227
},
{
"law": "育児休業給付",
"cat": "育児休業給付金",
"q": "パパ・ママ育休プラスを取得する場合であっても、夫婦ともに被保険者であるときは、育児休業給付金の支給期間が通算される。",
"a": false,
"exp": "×。法61条の7。夫婦ともに被保険者である場合であっても、育児休業給付金の支給期間は通算されない。",
"page": 226
},
{
"law": "育児休業給付",
"cat": "育児休業給付金",
"q": "育児休業給付金の支給対象となるには、支給単位期間において公共職業安定所長が就業していると認める日数が<b>10日以下</b>(10日を超える場合は就業していると認める時間が80時間以下)であることが必要である。",
"a": true,
"exp": "〇。則101条の22。就業日数10日以下(10日超の場合は80時間以下)であることが要件である。",
"page": 222
},
{
"law": "育児休業給付",
"cat": "出生時育児休業給付金",
"q": "出生時育児休業給付金は、その子の出生の日から起算して8週間を経過する日の翌日までの期間内に<b>4週間以内</b>の期間を定めて当該子を養育するための休業をした場合に支給される。",
"a": true,
"exp": "〇。法61条の8第1項。出生後8週間を経過する日の翌日までの期間内に4週間以内の休業をした場合に支給される。",
"page": 232
},
{
"law": "育児休業給付",
"cat": "出生時育児休業給付金",
"q": "出生時育児休業給付金の額は、休業開始時賃金日額に支給日数(28日を限度)を乗じて得た額の<b>100分の67</b>に相当する額である。",
"a": true,
"exp": "〇。法61条の8第4項。休業開始時賃金日額に支給日数(28日限度)を乗じた額の100分の67に相当する額である。",
"page": 234
},
{
"law": "育児休業給付",
"cat": "出生時育児休業給付金",
"q": "同一の子について被保険者がした出生時育児休業の日数を合算して得た日数が<b>28日</b>に達した日後の出生時育児休業については、出生時育児休業給付金は支給されない。",
"a": true,
"exp": "〇。法61条の8第2項。合算日数が28日に達した日後及び3回目以後の出生時育児休業は支給されない。",
"page": 234
},
{
"law": "育児休業給付",
"cat": "出生後休業支援給付金",
"q": "出生後休業支援給付金は、対象期間内にした出生後休業の日数が通算して<b>14日以上</b>であること等の要件に該当するときに支給される。",
"a": true,
"exp": "〇。法61条の10第1項。対象期間内の出生後休業の日数が通算14日以上であること等が要件である。",
"page": 236
},
{
"law": "育児休業給付",
"cat": "出生後休業支援給付金",
"q": "出生後休業支援給付金の額は、賃金日額に相当する額に出生後休業をした日数(28日を限度)を乗じて得た額の<b>100分の30</b>に相当する額である。",
"a": false,
"exp": "×。法61条の10第6項。出生後休業支援給付金の額は日数(28日限度)を乗じた額の「100分の13」に相当する額である。",
"page": 238
},
{
"law": "育児休業給付",
"cat": "育児時短就業給付金",
"q": "育児時短就業給付金は、被保険者がその<b>2歳に満たない子</b>を養育するための所定労働時間を短縮することによる就業をした場合に、支給対象月について支給される。",
"a": true,
"exp": "〇。法61条の12第1項。2歳に満たない子を養育するための育児時短就業をした場合に支給される。",
"page": 240
},
{
"law": "育児休業給付",
"cat": "育児時短就業給付金",
"q": "育児時短就業給付金の額は、原則として、支給対象月の賃金額が「育児時短就業開始時賃金日額×30」の額の100分の90未満である場合、支給対象月の賃金額の<b>100分の10</b>に相当する額である。",
"a": true,
"exp": "〇。法61条の12第6項。賃金額が100分の90未満の場合は賃金額の100分の10に相当する額である。",
"page": 242
},
{
"law": "育児休業給付",
"cat": "育児時短就業給付金",
"q": "育児時短就業給付金の支給を受けることができる者が、同一の就業につき高年齢雇用継続基本給付金の支給を受けたときは、育児時短就業給付金は支給されない。",
"a": true,
"exp": "〇。法61条の12第10項。高年齢雇用継続基本給付金等を受けたときは育児時短就業給付金は支給されない(支給調整)。",
"page": 243
},
{
"law": "雇用保険二事業",
"cat": "雇用保険二事業",
"q": "雇用保険二事業は、雇用安定事業及び<b>能力開発事業</b>の2つの事業に区分されている。",
"a": true,
"exp": "〇。法62条等。雇用保険二事業は雇用安定事業及び能力開発事業の2つに区分される。",
"page": 246
},
{
"law": "雇用保険二事業",
"cat": "雇用安定事業",
"q": "雇用安定事業は、被保険者、被保険者であった者及び<b>被保険者になろうとする者</b>に関して行われる。",
"a": true,
"exp": "〇。法62条1項。雇用安定事業は被保険者等(被保険者・被保険者であった者・被保険者になろうとする者)に関して行われる。",
"page": 246
},
{
"law": "雇用保険二事業",
"cat": "助成金",
"q": "雇用保険二事業として支給される助成金等には、雇用保険法の受給権保護の規定は適用されず、租税その他の公課の対象となる。",
"a": true,
"exp": "〇。法11条、12条参照。二事業に係る給付金には受給権保護・公課の禁止の規定は適用されない。",
"page": 248
},
{
"law": "雇用保険二事業",
"cat": "助成金等の不支給",
"q": "雇用関係助成金は、過去<b>5年以内</b>に偽りその他不正の行為により給付金の支給を受け、又は受けようとした事業主等に対しては支給されない。",
"a": true,
"exp": "〇。則120条の2。過去5年以内に不正受給した事業主等に対しては支給されない。",
"page": 249
},
{
"law": "雇用保険二事業",
"cat": "就職支援法事業",
"q": "政府は、能力開発事業として、求職者支援法に規定する特定求職者に対して<b>職業訓練受講給付金</b>を支給することができる。",
"a": true,
"exp": "〇。法64条。就職支援法事業として特定求職者に職業訓練受講給付金を支給できる。",
"page": 251
},
{
"law": "雇用保険二事業",
"cat": "事業の実施",
"q": "政府は、雇用安定事業及び能力開発事業の一部を<b>独立行政法人高齢・障害・求職者雇用支援機構</b>に行わせる。",
"a": true,
"exp": "〇。法62条3項、63条3項。雇用安定事業及び能力開発事業の一部を当該機構に行わせる。",
"page": 252
},
{
"law": "費用・不服申立て・その他",
"cat": "国庫負担",
"q": "失業等給付のうち、高年齢求職者給付金、就職促進給付及び高年齢雇用継続給付に要する費用については、<b>国庫負担は行われない</b>。",
"a": true,
"exp": "〇。法66条等。高年齢求職者給付金、就職促進給付、教育訓練給付(休暇給付金除く)、高年齢雇用継続給付には国庫負担はない。",
"page": 256
},
{
"law": "費用・不服申立て・その他",
"cat": "国庫負担",
"q": "育児休業給付に要する費用に係る国庫負担の割合は、<b>4分の1</b>である。",
"a": false,
"exp": "×。法66条。育児休業給付及び雇用継続給付(介護休業給付金に限る)の国庫負担割合は「8分の1」である。",
"page": 256
},
{
"law": "費用・不服申立て・その他",
"cat": "国庫負担",
"q": "就職支援法事業以外の雇用保険二事業には、国庫負担はなく、事業主が負担する保険料で賄われる。",
"a": true,
"exp": "〇。法。就職支援法事業以外の二事業には国庫負担はなく、事業主負担の保険料で賄われる。",
"page": 257
},
{
"law": "費用・不服申立て・その他",
"cat": "子ども・子育て支援納付金",
"q": "出生後休業支援給付及び育児時短就業給付に要する費用は、子ども・子育て支援法の規定により政府が徴収する<b>子ども・子育て支援納付金</b>をもって充てるものとされている。",
"a": true,
"exp": "〇。法68条の2。出生後休業支援給付及び育児時短就業給付の費用は子ども・子育て支援納付金をもって充てる。",
"page": 258
},
{
"law": "費用・不服申立て・その他",
"cat": "審査請求",
"q": "被保険者の資格の取得・喪失の確認に関する処分等に不服のある者は、<b>雇用保険審査官</b>に対して審査請求をし、その決定に不服のある者は労働保険審査会に対して再審査請求をすることができる。",
"a": true,
"exp": "〇。法69条1項。雇用保険審査官への審査請求、労働保険審査会への再審査請求ができる。",
"page": 259
},
{
"law": "費用・不服申立て・その他",
"cat": "審査請求期間",
"q": "審査請求は、処分があったことを知った日の翌日から起算して<b>2か月</b>を経過したときは、することができない。",
"a": false,
"exp": "×。労働保険審査官及び労働保険審査会法。審査請求は処分を知った日の翌日から起算して「3か月」を経過したときはできない。再審査請求が2か月である。",
"page": 259
},
{
"law": "費用・不服申立て・その他",
"cat": "審査請求",
"q": "審査請求をしている者は、審査請求をした日の翌日から起算して<b>3か月</b>を経過しても決定がないときは、審査請求が棄却されたものとみなすことができる。",
"a": true,
"exp": "〇。法69条2項。審査請求日の翌日から3か月経過しても決定がないときは棄却されたものとみなすことができる。",
"page": 259
},
{
"law": "費用・不服申立て・その他",
"cat": "不服申立ての前置",
"q": "確認等の処分の取消しの訴えは、当該処分についての審査請求に対する雇用保険審査官の決定を経た後でなければ提起することができない。",
"a": true,
"exp": "〇。法71条。処分の取消しの訴えは雇用保険審査官の決定を経た後でなければ提起できない(審査請求前置)。",
"page": 260
},
{
"law": "費用・不服申立て・その他",
"cat": "時効",
"q": "失業等給付等の支給を受け、又はその返還を受ける権利は、これらを行使することができる時から<b>2年</b>を経過したときは、時効によって消滅する。",
"a": true,
"exp": "〇。法74条1項。失業等給付等の支給を受ける権利等は2年の時効で消滅する。",
"page": 262
},
{
"law": "費用・不服申立て・その他",
"cat": "時効",
"q": "被保険者の資格の取得又は喪失の確認に係る請求をする権利は、2年の消滅時効の対象である。",
"a": false,
"exp": "×。法74条。資格の取得・喪失の確認に係る請求をする権利は、この時効の規定の対象ではない。",
"page": 262
},
{
"law": "費用・不服申立て・その他",
"cat": "診断",
"q": "行政庁は、求職者給付の支給を行うため必要があると認めるときは、失業の認定を受けようとする者等に対して、その指定する<b>医師の診断</b>を受けるべきことを命ずることができる。",
"a": true,
"exp": "〇。法78条。求職者給付の支給のため必要があるときは指定する医師の診断を受けるべきことを命ずることができる。",
"page": 264
},
{
"law": "費用・不服申立て・その他",
"cat": "罰則",
"q": "事業主が被保険者に関する届出をせず、又は偽りの届出をした場合等は、<b>6か月以下の拘禁刑又は30万円以下の罰金</b>に処せられる。",
"a": true,
"exp": "〇。法83条。事業主等が届出義務違反等をした場合は6か月以下の拘禁刑又は30万円以下の罰金に処せられる。",
"page": 265
},
{
"law": "費用・不服申立て・その他",
"cat": "証明書の交付",
"q": "離職した者は、従前の事業主等に対して、求職者給付の支給を受けるために必要な証明書の交付を請求することができる。",
"a": true,
"exp": "〇。法76条3項。離職した者は従前の事業主等に求職者給付の支給に必要な証明書の交付を請求できる。",
"page": 265
}
]